{
  "id": "text_content",
  "type": "SharedSlice",
  "name": "TextContent",
  "description": "TextContent",
  "variations": [
    {
      "id": "default-slice",
      "name": "Default slice",
      "docURL": "...",
      "version": "sktwi1xtmkfgx8626",
      "description": "TextContent",
      "primary": {
        "distanceToBottom": {
          "type": "Select",
          "config": {
            "label": "Distance To Bottom",
            "placeholder": "",
            "options": [
              "none",
              "small",
              "large"
            ]
          }
        },
        "line": {
          "type": "Boolean",
          "config": {
            "label": "Line",
            "default_value": false,
            "placeholder_true": "true",
            "placeholder_false": "false"
          }
        },
        "distanceToTop": {
          "type": "Select",
          "config": {
            "label": "Distance To Top",
            "placeholder": "",
            "options": [
              "small",
              "medium",
              "large"
            ]
          }
        },
        "intro": {
          "type": "Boolean",
          "config": {
            "label": "Intro",
            "default_value": false,
            "placeholder_true": "true",
            "placeholder_false": "false"
          }
        },
        "backgroundColor": {
          "type": "Select",
          "config": {
            "label": "Background-Color",
            "placeholder": "Background-Color",
            "options": [
              "yellow",
              "red",
              "purple",
              "lightblue",
              "darkblue",
              "green"
            ]
          }
        },
        "fullViewportHeight": {
          "type": "Boolean",
          "config": {
            "label": "Full Viewport Height",
            "default_value": false,
            "placeholder_true": "true",
            "placeholder_false": "false"
          }
        }
      },
      "items": {
        "Content": {
          "config": {
            "label": "Content",
            "placeholder": "",
            "allowTargetBlank": true,
            "multi": "paragraph,preformatted,heading2,heading4,strong,em,hyperlink,image,embed,list-item,o-list-item,rtl"
          },
          "type": "StructuredText"
        },
        "subline": {
          "type": "Boolean",
          "config": {
            "label": "Subline",
            "placeholder_false": "false",
            "placeholder_true": "true",
            "default_value": false
          }
        }
      },
      "imageUrl": "https://images.prismic.io/slice-machine/621a5ec4-0387-4bc5-9860-2dd46cbc07cd_default_ss.png?auto=compress,format"
    }
  ]
}